spellchecker_ml/__init__.py
spellchecker_ml/spellchecker_ml/__init__.py
spellchecker_ml/spellchecker_ml/spellchecker_ml.py
spellchecker_ml-0.1.4.dist-info/METADATA
spellchecker_ml-0.1.4.dist-info/WHEEL
spellchecker_ml-0.1.4.dist-info/top_level.txt
spellchecker_ml-0.1.4.dist-info/RECORD
