Metadata-Version: 2.1
Name: spellchecker-ml
Version: 0.1.4
Summary: Spellchecker that makes use of a hidden markov model
Home-page: https://github.com/EricSchles/spellchecker_ml
Author: Eric Schles
Author-email: ericschles@gmail.com
License: MIT
Platform: UNKNOWN
Classifier: License :: OSI Approved :: MIT License
Classifier: Programming Language :: Python :: 3
Classifier: Programming Language :: Python :: 3.6
Classifier: Programming Language :: Python :: 3.7
Requires-Dist: pyspellchecker
Requires-Dist: autocomplete
